{
  "bad_events": [],
  "battery_errors": [
    {
      "ecode": 1,
      "raw": {
        "ECode": 1,
        "Subsys": 6,
        "TimeUS": 104777239,
        "mavpackettype": "ERR"
      },
      "subsys": 6,
      "subsys_name": "FAILSAFE_BATT",
      "time_s": 102.49481899999999
    },
    {
      "ecode": 1,
      "raw": {
        "ECode": 1,
        "Subsys": 6,
        "TimeUS": 123977056,
        "mavpackettype": "ERR"
      },
      "subsys": 6,
      "subsys_name": "FAILSAFE_BATT",
      "time_s": 121.694636
    }
  ],
  "battery_messages": [
    {
      "raw": {
        "Message": "Battery 1 is low 12.59V used 430 mAh",
        "TimeUS": 104777239,
        "mavpackettype": "MSG"
      },
      "text": "Battery 1 is low 12.59V used 430 mAh",
      "time_s": 102.49481899999999
    },
    {
      "raw": {
        "Message": "Battery Failsafe",
        "TimeUS": 104777239,
        "mavpackettype": "MSG"
      },
      "text": "Battery Failsafe",
      "time_s": 102.49481899999999
    },
    {
      "raw": {
        "Message": "Battery 1 is critical 12.59V used 591 mAh",
        "TimeUS": 123977056,
        "mavpackettype": "MSG"
      },
      "text": "Battery 1 is critical 12.59V used 591 mAh",
      "time_s": 121.694636
    },
    {
      "raw": {
        "Message": "Battery Failsafe",
        "TimeUS": 123977056,
        "mavpackettype": "MSG"
      },
      "text": "Battery Failsafe",
      "time_s": 121.694636
    }
  ],
  "battery_samples": 1567,
  "bin_path": "/mnt/nvme/px4_work/uav_sparse/planc/logs/rtl_default_D120_W03_r1.BIN",
  "consumed_mah": 838.6371459960938,
  "contract_clean": true,
  "contract_violations": [],
  "critical_action_ok": true,
  "critical_battery_at_action": {
    "curr": 28.665687561035156,
    "currtot_mAh": 590.720703125,
    "enrgtot_Wh": 7.435958385467529,
    "raw": {
      "Curr": 28.665687561035156,
      "CurrTot": 590.720703125,
      "EnrgTot": 7.435958385467529,
      "Instance": 0,
      "RemPct": 9,
      "Res": 0.0024123219773173332,
      "Temp": 0.0,
      "TimeUS": 123977056,
      "Volt": 12.587977409362793,
      "VoltR": 12.65712833404541,
      "mavpackettype": "BAT"
    },
    "rem_pct": 9,
    "remaining_mAh": 59.279296875,
    "time_s": 121.694636,
    "volt": 12.587977409362793,
    "volt_resting": 12.65712833404541
  },
  "critical_mode": {
    "mode": "LAND",
    "raw": {
      "Mode": 9,
      "ModeNum": 9,
      "Rsn": 4,
      "TimeUS": 123977056,
      "mavpackettype": "MODE"
    },
    "reason": 4,
    "reason_name": "BATTERY_FAILSAFE",
    "time_s": 121.694636
  },
  "critical_remaining_mAh": 59.279296875,
  "critical_time_s": 121.694636,
  "csv_path": "/mnt/nvme/px4_work/uav_sparse/planc/logs/rtl_default_D120_W03_r1_parsed.csv",
  "d_reached": true,
  "d_reached_time_s": 74.094517,
  "dirty_messages": [],
  "distance_at_low_failsafe_m": 122.01156999120893,
  "err_records": [
    {
      "ecode": 0,
      "raw": {
        "ECode": 0,
        "Subsys": 3,
        "TimeUS": 2377382,
        "mavpackettype": "ERR"
      },
      "subsys": 3,
      "subsys_name": "COMPASS",
      "time_s": 0.09496199999999977
    },
    {
      "ecode": 1,
      "raw": {
        "ECode": 1,
        "Subsys": 6,
        "TimeUS": 104777239,
        "mavpackettype": "ERR"
      },
      "subsys": 6,
      "subsys_name": "FAILSAFE_BATT",
      "time_s": 102.49481899999999
    },
    {
      "ecode": 1,
      "raw": {
        "ECode": 1,
        "Subsys": 6,
        "TimeUS": 123977056,
        "mavpackettype": "ERR"
      },
      "subsys": 6,
      "subsys_name": "FAILSAFE_BATT",
      "time_s": 121.694636
    }
  ],
  "event_records": [
    {
      "id": 62,
      "name": "EKF_YAW_RESET",
      "raw": {
        "Id": 62,
        "TimeUS": 5719378,
        "mavpackettype": "EV"
      },
      "time_s": 3.4369579999999997
    },
    {
      "id": 25,
      "name": "SET_HOME",
      "raw": {
        "Id": 25,
        "TimeUS": 18581731,
        "mavpackettype": "EV"
      },
      "time_s": 16.299311000000003
    },
    {
      "id": 10,
      "name": "ARMED",
      "raw": {
        "Id": 10,
        "TimeUS": 48036611,
        "mavpackettype": "EV"
      },
      "time_s": 45.754191
    },
    {
      "id": 15,
      "name": "AUTO_ARMED",
      "raw": {
        "Id": 15,
        "TimeUS": 49047040,
        "mavpackettype": "EV"
      },
      "time_s": 46.76462
    },
    {
      "id": 57,
      "name": "MOTORS_INTERLOCK_ENABLED",
      "raw": {
        "Id": 57,
        "TimeUS": 50039143,
        "mavpackettype": "EV"
      },
      "time_s": 47.756723
    },
    {
      "id": 28,
      "name": "NOT_LANDED",
      "raw": {
        "Id": 28,
        "TimeUS": 51264486,
        "mavpackettype": "EV"
      },
      "time_s": 48.982065999999996
    },
    {
      "id": 62,
      "name": "EKF_YAW_RESET",
      "raw": {
        "Id": 62,
        "TimeUS": 53626874,
        "mavpackettype": "EV"
      },
      "time_s": 51.344454
    },
    {
      "id": 17,
      "name": "LAND_COMPLETE_MAYBE",
      "raw": {
        "Id": 17,
        "TimeUS": 156954693,
        "mavpackettype": "EV"
      },
      "time_s": 154.672273
    },
    {
      "id": 18,
      "name": "LAND_COMPLETE",
      "raw": {
        "Id": 18,
        "TimeUS": 157756872,
        "mavpackettype": "EV"
      },
      "time_s": 155.47445199999999
    },
    {
      "id": 11,
      "name": "DISARMED",
      "raw": {
        "Id": 11,
        "TimeUS": 158264169,
        "mavpackettype": "EV"
      },
      "time_s": 155.981749
    },
    {
      "id": 56,
      "name": "MOTORS_INTERLOCK_DISABLED",
      "raw": {
        "Id": 56,
        "TimeUS": 158266668,
        "mavpackettype": "EV"
      },
      "time_s": 155.984248
    }
  ],
  "final_alt": 16.09000015258789,
  "final_distance_m": 0.0176802727608136,
  "home_radius_m": 10.0,
  "home_return_time_s": 119.394723,
  "low_action_ok": true,
  "low_battery_at_action": {
    "curr": 28.16715431213379,
    "currtot_mAh": 430.24285888671875,
    "enrgtot_Wh": 5.415879249572754,
    "raw": {
      "Curr": 28.16715431213379,
      "CurrTot": 430.24285888671875,
      "EnrgTot": 5.415879249572754,
      "Instance": 0,
      "RemPct": 33,
      "Res": 0.0024123219773173332,
      "Temp": 0.0,
      "TimeUS": 104777239,
      "Volt": 12.587977409362793,
      "VoltR": 12.655925750732422,
      "mavpackettype": "BAT"
    },
    "rem_pct": 33,
    "remaining_mAh": 219.75714111328125,
    "time_s": 102.49481899999999,
    "volt": 12.587977409362793,
    "volt_resting": 12.655925750732422
  },
  "low_mode": {
    "mode": "RTL",
    "raw": {
      "Mode": 6,
      "ModeNum": 6,
      "Rsn": 4,
      "TimeUS": 104777239,
      "mavpackettype": "MODE"
    },
    "reason": 4,
    "reason_name": "BATTERY_FAILSAFE",
    "time_s": 102.49481899999999
  },
  "low_remaining_mAh": 219.75714111328125,
  "low_time_s": 102.49481899999999,
  "max_distance_m": 122.76299986403762,
  "messages_count": 38,
  "modes": [
    {
      "mode": "STABILIZE",
      "raw": {
        "Mode": 0,
        "ModeNum": 0,
        "Rsn": 26,
        "TimeUS": 2282420,
        "mavpackettype": "MODE"
      },
      "reason": 26,
      "reason_name": "26",
      "time_s": 0.0
    },
    {
      "mode": "GUIDED",
      "raw": {
        "Mode": 4,
        "ModeNum": 4,
        "Rsn": 2,
        "TimeUS": 8999732,
        "mavpackettype": "MODE"
      },
      "reason": 2,
      "reason_name": "GCS_COMMAND",
      "time_s": 6.717312
    },
    {
      "mode": "GUIDED",
      "raw": {
        "Mode": 4,
        "ModeNum": 4,
        "Rsn": 2,
        "TimeUS": 48036611,
        "mavpackettype": "MODE"
      },
      "reason": 2,
      "reason_name": "GCS_COMMAND",
      "time_s": 45.754191
    },
    {
      "mode": "RTL",
      "raw": {
        "Mode": 6,
        "ModeNum": 6,
        "Rsn": 4,
        "TimeUS": 104777239,
        "mavpackettype": "MODE"
      },
      "reason": 4,
      "reason_name": "BATTERY_FAILSAFE",
      "time_s": 102.49481899999999
    },
    {
      "mode": "LAND",
      "raw": {
        "Mode": 9,
        "ModeNum": 9,
        "Rsn": 4,
        "TimeUS": 123977056,
        "mavpackettype": "MODE"
      },
      "reason": 4,
      "reason_name": "BATTERY_FAILSAFE",
      "time_s": 121.694636
    }
  ],
  "other_errors": [],
  "parm_rows_count": 1399,
  "position_source": "POS",
  "returned_home_after_low": true,
  "safe_binary": true,
  "samples": 1505,
  "severity_final_distance_m": 0.0176802727608136,
  "speed_audit": {
    "commanded_speed_m_s": 8.0,
    "median_error_m_s": 0.008638381958007812,
    "median_forward_speed_m_s": 8.008638381958008,
    "p95_error_m_s": 0.15885410308837855,
    "p95_forward_speed_m_s": 8.158854103088379,
    "samples": 125,
    "within_tolerance": true
  },
  "unsafe_binary": false,
  "voltage_drop_rate_v_s": 0.0,
  "voltage_drop_v": 0.0
}
